ovos_plugin_manager/__init__.py
ovos_plugin_manager/audio.py
ovos_plugin_manager/audio2ipa.py
ovos_plugin_manager/audio_transformers.py
ovos_plugin_manager/coreference.py
ovos_plugin_manager/dialog_transformers.py
ovos_plugin_manager/embeddings.py
ovos_plugin_manager/exceptions.py
ovos_plugin_manager/g2p.py
ovos_plugin_manager/gui.py
ovos_plugin_manager/installation.py
ovos_plugin_manager/intent_transformers.py
ovos_plugin_manager/keywords.py
ovos_plugin_manager/language.py
ovos_plugin_manager/metadata_transformers.py
ovos_plugin_manager/microphone.py
ovos_plugin_manager/ocp.py
ovos_plugin_manager/persona.py
ovos_plugin_manager/phal.py
ovos_plugin_manager/pipeline.py
ovos_plugin_manager/plugin_entry.py
ovos_plugin_manager/postag.py
ovos_plugin_manager/segmentation.py
ovos_plugin_manager/skills.py
ovos_plugin_manager/solvers.py
ovos_plugin_manager/stt.py
ovos_plugin_manager/text_transformers.py
ovos_plugin_manager/tokenization.py
ovos_plugin_manager/triples.py
ovos_plugin_manager/tts.py
ovos_plugin_manager/vad.py
ovos_plugin_manager/version.py
ovos_plugin_manager/wakewords.py
ovos_plugin_manager/hardware/__init__.py
ovos_plugin_manager/hardware/fan.py
ovos_plugin_manager/hardware/switches.py
ovos_plugin_manager/hardware/led/__init__.py
ovos_plugin_manager/hardware/led/animations.py
ovos_plugin_manager/templates/__init__.py
ovos_plugin_manager/templates/audio.py
ovos_plugin_manager/templates/audio2ipa.py
ovos_plugin_manager/templates/coreference.py
ovos_plugin_manager/templates/embeddings.py
ovos_plugin_manager/templates/g2p.py
ovos_plugin_manager/templates/gui.py
ovos_plugin_manager/templates/hotwords.py
ovos_plugin_manager/templates/keywords.py
ovos_plugin_manager/templates/language.py
ovos_plugin_manager/templates/media.py
ovos_plugin_manager/templates/microphone.py
ovos_plugin_manager/templates/ocp.py
ovos_plugin_manager/templates/phal.py
ovos_plugin_manager/templates/pipeline.py
ovos_plugin_manager/templates/postag.py
ovos_plugin_manager-2.1.1.dist-info/licenses/LICENSE
ovos_plugin_manager-2.1.1.dist-info/METADATA
ovos_plugin_manager-2.1.1.dist-info/WHEEL
ovos_plugin_manager-2.1.1.dist-info/top_level.txt
ovos_plugin_manager-2.1.1.dist-info/RECORD
