Metadata-Version: 2.4
Name: ovos-plugin-manager
Version: 2.1.1
Summary: OpenVoiceOS plugin manager
Home-page: https://github.com/OpenVoiceOS/OVOS-plugin-manager
Author: jarbasAi
Author-email: jarbas@openvoiceos.com
License: Apache-2.0
License-File: LICENSE
Requires-Dist: ovos-utils<1.0.0,>=0.2.1
Requires-Dist: ovos_bus_client<2.0.0,>=0.0.8
Requires-Dist: ovos-config<3.0.0,>=0.0.12
Requires-Dist: combo_lock~=0.3
Requires-Dist: requests~=2.32
Requires-Dist: quebra_frases
Requires-Dist: langcodes~=3.5.0
Requires-Dist: importlib_metadata
Requires-Dist: setuptools; python_version >= "3.12"
Requires-Dist: standard-aifc; python_version >= "3.13"
Requires-Dist: audioop-lts; python_version >= "3.13"
Dynamic: author
Dynamic: author-email
Dynamic: description
Dynamic: description-content-type
Dynamic: home-page
Dynamic: license
Dynamic: license-file
Dynamic: requires-dist
Dynamic: summary
